vr_idt/__init__.py
vr_idt/vr_idt.py
vr_idt-0.0.5.dist-info/LICENSE.txt
vr_idt-0.0.5.dist-info/METADATA
vr_idt-0.0.5.dist-info/WHEEL
vr_idt-0.0.5.dist-info/top_level.txt
vr_idt-0.0.5.dist-info/RECORD
