Metadata-Version: 2.1
Name: vr-idt
Version: 0.0.5
Summary: Virtual reality eye tracking event classification algorithm
Home-page: https://github.com/ajpkim/vr-idt
Author: Alex Kim
Author-email: dev@ajpkim.com
Classifier: Programming Language :: Python :: 3
Classifier: License :: OSI Approved :: GNU General Public License v3 (GPLv3)
Classifier: Operating System :: OS Independent
Requires-Python: >=3.8
License-File: LICENSE.txt
Requires-Dist: pandas (>=1.4.0)
